lsstvaultutils/__init__.py
lsstvaultutils/_version.py
lsstvaultutils/multisecret.py
lsstvaultutils/recursivedeleter.py
lsstvaultutils/timeformatter.py
lsstvaultutils/tokenadmin.py
lsstvaultutils/vaultconfig.py
lsstvaultutils-0.3.1.dist-info/LICENSE
lsstvaultutils-0.3.1.dist-info/METADATA
lsstvaultutils-0.3.1.dist-info/WHEEL
lsstvaultutils-0.3.1.dist-info/entry_points.txt
lsstvaultutils-0.3.1.dist-info/top_level.txt
lsstvaultutils-0.3.1.dist-info/RECORD
