Metadata-Version: 2.1
Name: lsstvaultutils
Version: 0.3.1
Summary: Tools for manipulating the Rubin Observatory Vault installation
License: The MIT License (MIT)
Project-URL: Source, https://github.com/lsst-sqre/lsstvaultutils
Keywords: rubin,lsst
Classifier: Development Status :: 4 - Beta
Classifier: License :: OSI Approved :: MIT License
Classifier: Programming Language :: Python
Classifier: Programming Language :: Python :: 3
Classifier: Programming Language :: Python :: 3.9
Classifier: Natural Language :: English
Classifier: Operating System :: POSIX
Requires-Python: >=3.8
License-File: LICENSE
Requires-Dist: click
Requires-Dist: hvac
Provides-Extra: dev
Requires-Dist: pytest ; extra == 'dev'
Requires-Dist: mypy ; extra == 'dev'
Requires-Dist: coverage ; extra == 'dev'
